<?xml version="1.0" encoding="UTF-8"?>
<objects serializationModel="Studio.02.01.00">
	<object class="AudioFile" id="{6f833ed3-4f34-461c-bcaa-008b30892020}">
		<property name="assetPath">
			<value>johnj_wafare_gun_pistol_silenced_walther_pp7.mp3</value>
		</property>
		<property name="frequencyInKHz">
			<value>44.0999985</value>
		</property>
		<property name="channelCount">
			<value>2</value>
		</property>
		<property name="length">
			<value>0.47020408163265304</value>
		</property>
		<relationship name="masterAssetFolder">
			<destination>{71420eeb-9855-4584-bad4-862ecca1f486}</destination>
		</relationship>
	</object>
</objects>
